{
  "gitSyncId": "682c3f379fbebc47e63ede10_b84a87de-59c9-4bf7-94ab-20514bac4e01",
  "id": "ManageTimeSheet_clientsDropDownList.getClientsDropdown",
  "pluginId": "js-plugin",
  "pluginType": "JS",
  "unpublishedAction": {
    "actionConfiguration": {
      "encodeParamsToggle": true,
      "jsArguments": [],
      "paginationType": "NONE",
      "timeoutInMillisecond": 10000
    },
    "collectionId": "ManageTimeSheet_clientsDropDownList",
    "confirmBeforeExecute": false,
    "datasource": {
      "isAutoGenerated": false,
      "name": "UNUSED_DATASOURCE",
      "pluginId": "js-plugin"
    },
    "dynamicBindingPathList": [
      {
        "key": "body"
      }
    ],
    "fullyQualifiedName": "clientsDropDownList.getClientsDropdown",
    "name": "getClientsDropdown",
    "pageId": "ManageTimeSheet",
    "runBehaviour": "MANUAL",
    "userSetOnLoad": false
  }
}